README.rst
setup.py
addresshunt/__init__.py
addresshunt/address.py
addresshunt/client.py
addresshunt/exceptions.py
addresshunt.egg-info/PKG-INFO
addresshunt.egg-info/SOURCES.txt
addresshunt.egg-info/dependency_links.txt
addresshunt.egg-info/entry_points.txt
addresshunt.egg-info/requires.txt
addresshunt.egg-info/top_level.txt