Metadata-Version: 2.1
Name: addresshunt
Version: 1.2
Summary: Python package for address validations
Home-page: https://addresshunt.com.au/#home
Author: AddressHunt
Author-email: contact@addresshunt.com.au
License: UNKNOWN
Platform: UNKNOWN
